setup.py
std_domain.egg-info/PKG-INFO
std_domain.egg-info/SOURCES.txt
std_domain.egg-info/dependency_links.txt
std_domain.egg-info/pbr.json
std_domain.egg-info/requires.txt
std_domain.egg-info/top_level.txt
stddomain/__init__.py
stddomain/domain.py
tests/__init__.py
tests/test_domain.py