Metadata-Version: 1.1
Name: std-domain
Version: 0.0.5
Summary: A library for standarized Domain objects
Home-page: https://github.com/EvanDarwin/std-domain
Author: Evan Darwin
Author-email: evan@relta.net
License: proprietary
Keywords: international domain library
Platform: UNKNOWN
Classifier: License :: Other/Proprietary License
Classifier: Natural Language :: English
Classifier: Operating System :: OS Independent
Classifier: Topic :: Software Development :: Internationalization
